{
  "type": "header",
  "name": "Header",
  "sections": {
    "header": {
      "type": "header",
      "blocks": {
        "a1": {
          "type": "announcement",
          "settings": {
            "text": "Free UK delivery over ",
            "highlight": "£40",
            "text_after": ""
          }
        },
        "a2": {
          "type": "announcement",
          "settings": {
            "text": "Singles condition-checked under lamp",
            "highlight": "",
            "text_after": ""
          }
        },
        "a3": {
          "type": "announcement",
          "settings": {
            "text": "New sealed drops weekly · ",
            "highlight": "follow restocks",
            "text_after": ""
          }
        }
      },
      "block_order": ["a1", "a2", "a3"],
      "settings": {
        "show_announcement": true,
        "logo_text": "Kori Collectibles",
        "menu": "main-menu"
      }
    }
  },
  "order": ["header"]
}
